disko/__init__.py
disko/bayes_cli.py
disko/cli.py
disko/disko.py
disko/draw_cli.py
disko/draw_sky.py
disko/fov/__init__.py
disko/fov/factory.py
disko/healpix_sphere.py
disko/multivariate_gaussian.py
disko/parser_support.py
disko/projection_lsqr.py
disko/resolution.py
disko/sphere.py
disko/sphere_mesh.py
disko/svd_cli.py
disko/telescope_operator.py
disko/tests/__init__.py
disko/tests/test_disko.py
disko/tests/test_meshsphere.py
disko/tests/test_multivariate.py
disko/tests/test_projection_lsqr.py
disko/tests/test_pylops_operator.py
disko/tests/test_sphere.py
disko/tests/test_subsphere.py
disko/tests/test_telescope_operator.py
disko/util.py
disko-1.0.8.dist-info/METADATA
disko-1.0.8.dist-info/WHEEL
disko-1.0.8.dist-info/entry_points.txt
disko-1.0.8.dist-info/licenses/LICENSE.txt
disko-1.0.8.dist-info/RECORD
