Metadata-Version: 2.4
Name: disko
Version: 1.0.8
Summary: Discrete Sky Operator (DiSkO) Aperture Synthesis Radio Imaging
License: GPLv3
License-File: LICENSE.txt
Author: Tim Molteno
Author-email: tim@elec.ac.nz
Requires-Python: >=3.11,<3.14
Classifier: License :: Other/Proprietary License
Classifier: Programming Language :: Python :: 3
Classifier: Programming Language :: Python :: 3.11
Classifier: Programming Language :: Python :: 3.12
Classifier: Programming Language :: Python :: 3.13
Provides-Extra: ms
Requires-Dist: dask-ms (>=0.2.25,<0.3.0)
Requires-Dist: h5py (>=3.7)
Requires-Dist: healpy (>=1.15.0,<2.0.0)
Requires-Dist: imageio (>=0.6.0b1)
Requires-Dist: matplotlib (>=3.1.0,<4.0.0)
Requires-Dist: numpy (>=1.2.1,<3.0.0)
Requires-Dist: pygmsh (>=7.1.17,<8.0.0)
Requires-Dist: pylops (>=2.0)
Requires-Dist: scikit-learn (>=1.0.1)
Requires-Dist: scipy (>=1.7.3)
Requires-Dist: svgwrite (>=1.4.3)
Requires-Dist: tart (>=1.4.0)
Requires-Dist: tart-tools (>=1.4.0)
Requires-Dist: tart2ms (>=0.7.1) ; extra == "ms"
Requires-Dist: tart2ms (>=0.7.3,<0.8.0)
Requires-Dist: toolz (>=0.11.2)
